admin_ordering/__init__.py
admin_ordering/admin.py
admin_ordering/models.py
admin_ordering/locale/de/LC_MESSAGES/django.mo
admin_ordering/locale/de/LC_MESSAGES/django.po
admin_ordering/locale/fr/LC_MESSAGES/django.mo
admin_ordering/locale/fr/LC_MESSAGES/django.po
admin_ordering/static/admin_ordering/admin_ordering-icon.svg
admin_ordering/static/admin_ordering/admin_ordering.css
admin_ordering/static/admin_ordering/admin_ordering.js
admin_ordering/static/admin_ordering/jquery-ui.min.css
admin_ordering/static/admin_ordering/jquery-ui.min.js
django_admin_ordering-0.19.1.dist-info/METADATA
django_admin_ordering-0.19.1.dist-info/WHEEL
django_admin_ordering-0.19.1.dist-info/licenses/AUTHORS
django_admin_ordering-0.19.1.dist-info/licenses/LICENSE
django_admin_ordering-0.19.1.dist-info/RECORD
