Metadata-Version: 2.3
Name: django-admin-ordering
Version: 0.19.1
Summary: Orderable change lists and inlines done right^Wsimple
Project-URL: Homepage, https://github.com/matthiask/django-admin-ordering/
Author-email: Matthias Kestenholz <mk@feinheit.ch>
License: BSD-3-Clause
Classifier: Development Status :: 5 - Production/Stable
Classifier: Environment :: Web Environment
Classifier: Framework :: Django
Classifier: Intended Audience :: Developers
Classifier: License :: OSI Approved :: BSD License
Classifier: Operating System :: OS Independent
Classifier: Programming Language :: Python
Classifier: Programming Language :: Python :: 3 :: Only
Classifier: Programming Language :: Python :: 3.10
Classifier: Programming Language :: Python :: 3.11
Classifier: Programming Language :: Python :: 3.12
Classifier: Programming Language :: Python :: 3.13
Classifier: Topic :: Internet :: WWW/HTTP :: Dynamic Content
Classifier: Topic :: Software Development
Classifier: Topic :: Software Development :: Libraries :: Application Frameworks
Requires-Python: >=3.10
Requires-Dist: django-js-asset>=2
Provides-Extra: tests
Requires-Dist: coverage; extra == 'tests'
